{"breakTimes":[],"hitObjects":[{"startTime":66,"position":[285,368],"objectName":"right","endTime":382},{"startTime":539,"position":[461,292],"endTime":855},{"startTime":1013,"position":[386,164],"objectName":"left"},{"startTime":1171,"position":[508,101]},{"startTime":1329,"position":[430,91],"objectName":"up","endTime":1645},{"startTime":1802,"position":[305,197]},{"startTime":1960,"position":[368,242],"objectName":"left"},{"startTime":2118,"position":[386,164],"objectName":"left"},{"startTime":2276,"position":[226,185],"objectName":"left"},{"startTime":2434,"position":[320,313],"objectName":"left"},{"startTime":2592,"position":[397,322],"objectName":"right","endTime":2908},{"startTime":3066,"position":[247,348],"objectName":"left","endTime":3382},{"startTime":3539,"position":[52,339],"objectName":"left"},{"startTime":3697,"position":[119,245]},{"startTime":3855,"position":[83,105],"objectName":"right"},{"startTime":4487,"position":[82,110],"objectName":"up"},{"startTime":5118,"position":[155,153],"objectName":"right","endTime":5434},{"startTime":5592,"position":[347,173],"objectName":"up","endTime":5908},{"startTime":6066,"position":[371,249],"objectName":"right","endTime":6224},{"startTime":6381,"position":[424,194],"objectName":"right","endTime":6697},{"startTime":6855,"position":[344,327],"objectName":"up"},{"startTime":7013,"position":[347,173],"objectName":"right"},{"startTime":7171,"position":[371,249],"objectName":"right"},{"startTime":7329,"position":[344,327],"objectName":"right"},{"startTime":7487,"position":[273,203],"objectName":"left"},{"startTime":7644,"position":[400,112],"objectName":"right","endTime":7802},{"startTime":7960,"position":[351,49],"objectName":"left"},{"startTime":8118,"position":[292,100],"endTime":8434},{"startTime":8592,"position":[94,94],"objectName":"up","endTime":8750},{"startTime":8908,"position":[96,100],"objectName":"left"},{"startTime":9539,"position":[99,106],"objectName":"up"},{"startTime":10171,"position":[159,158],"objectName":"right","endTime":10327},{"startTime":10487,"position":[436,166],"objectName":"left"},{"startTime":10644,"position":[368,114],"objectName":"right"},{"startTime":10723,"position":[368,114],"objectName":"left"},{"startTime":10802,"position":[368,114],"objectName":"up","endTime":10958},{"startTime":11118,"position":[436,166],"endTime":11274},{"startTime":11434,"position":[496,113],"objectName":"right"},{"startTime":11592,"position":[343,193]},{"startTime":11750,"position":[135,155],"endTime":11985},{"startTime":12066,"position":[281,136],"objectName":"left"},{"startTime":12223,"position":[300,261],"objectName":"right","endTime":12535},{"startTime":12697,"position":[371,39],"objectName":"right","endTime":12853},{"startTime":13013,"position":[226,218],"objectName":"left"},{"startTime":13171,"position":[146,249]},{"startTime":13250,"position":[146,249]},{"startTime":13329,"position":[146,249],"objectName":"right","endTime":13485},{"startTime":13644,"position":[229,137],"objectName":"left","endTime":13800},{"startTime":13960,"position":[260,344],"objectName":"right"},{"startTime":14118,"position":[429,286],"objectName":"up"},{"startTime":14276,"position":[314,215],"objectName":"up"},{"startTime":14434,"position":[483,158],"objectName":"up"},{"startTime":14592,"position":[277,144],"objectName":"up"},{"startTime":14750,"position":[433,229],"objectName":"left"},{"startTime":14908,"position":[308,280],"objectName":"left"},{"startTime":15066,"position":[464,366],"objectName":"up"},{"startTime":15223,"position":[183,313],"endTime":15379},{"startTime":15539,"position":[160,97],"objectName":"up","endTime":15774},{"startTime":15855,"position":[188,204],"objectName":"left","endTime":16011},{"startTime":16171,"position":[438,85]},{"startTime":16329,"position":[509,163],"objectName":"right"},{"startTime":16487,"position":[367,182],"objectName":"up","endTime":16643},{"startTime":16802,"position":[444,224],"objectName":"right"},{"startTime":16960,"position":[299,84],"objectName":"left"},{"startTime":17039,"position":[298,89],"objectName":"up"},{"startTime":17118,"position":[297,94],"objectName":"right"},{"startTime":17197,"position":[296,99],"objectName":"left"},{"startTime":17276,"position":[295,104],"objectName":"right"},{"startTime":17434,"position":[231,161],"objectName":"up","endTime":17590},{"startTime":17750,"position":[7,132],"objectName":"left"},{"startTime":17908,"position":[69,191]},{"startTime":18066,"position":[170,78],"objectName":"up"},{"startTime":18223,"position":[89,106],"objectName":"up"},{"startTime":18381,"position":[136,248],"objectName":"left"},{"startTime":18460,"position":[134,253],"objectName":"right"},{"startTime":18539,"position":[132,258]},{"startTime":18697,"position":[48,277],"endTime":18853},{"startTime":19013,"position":[197,315],"objectName":"up","endTime":19485},{"startTime":19644,"position":[176,180],"objectName":"up"},{"startTime":19802,"position":[238,133],"objectName":"up","endTime":19960},{"startTime":20118,"position":[372,230]},{"startTime":20197,"position":[372,230]},{"startTime":20276,"position":[372,230],"objectName":"right","endTime":20432},{"startTime":20592,"position":[297,182],"endTime":20827},{"startTime":20908,"position":[180,192],"objectName":"left","endTime":21064},{"startTime":21223,"position":[269,228],"objectName":"right"},{"startTime":21381,"position":[237,335]},{"startTime":21539,"position":[372,153],"endTime":21695},{"startTime":21855,"position":[389,312],"objectName":"up","endTime":22011},{"startTime":22171,"position":[387,136],"objectName":"left","endTime":22327},{"startTime":22487,"position":[373,328],"objectName":"up","endTime":22643},{"startTime":22802,"position":[196,197],"objectName":"up","endTime":22958},{"startTime":23118,"position":[324,33],"objectName":"up","endTime":23274},{"startTime":23434,"position":[348,228]},{"startTime":23513,"position":[350,232],"objectName":"up"},{"startTime":23592,"position":[353,236],"objectName":"right"},{"startTime":23750,"position":[220,280],"objectName":"up","endTime":23906},{"startTime":24066,"position":[37,146]},{"startTime":24223,"position":[132,211],"objectName":"right"},{"startTime":24381,"position":[203,122],"objectName":"left"},{"startTime":24539,"position":[102,54],"objectName":"left"},{"startTime":24618,"position":[103,59]},{"startTime":24697,"position":[104,64],"objectName":"right"},{"startTime":24776,"position":[105,69],"objectName":"up"},{"startTime":24855,"position":[106,74],"objectName":"left"},{"startTime":25013,"position":[203,122],"objectName":"up","endTime":25169},{"startTime":25329,"position":[471,39]},{"startTime":25487,"position":[356,151]},{"startTime":25644,"position":[385,70],"objectName":"right","endTime":25879},{"startTime":25960,"position":[436,166],"endTime":26116},{"startTime":26276,"position":[326,229],"objectName":"right","endTime":26432},{"startTime":26592,"position":[116,96]},{"startTime":26750,"position":[195,129],"objectName":"right"},{"startTime":26908,"position":[125,179],"objectName":"up"},{"startTime":27066,"position":[183,46],"objectName":"up"},{"startTime":27144,"position":[183,46],"objectName":"up"},{"startTime":27223,"position":[183,46],"objectName":"up"},{"startTime":27381,"position":[279,152],"objectName":"left"},{"startTime":27460,"position":[279,152],"objectName":"left"},{"startTime":27539,"position":[279,152],"objectName":"right"},{"startTime":27697,"position":[208,218]},{"startTime":27855,"position":[271,47],"endTime":28011},{"startTime":28171,"position":[486,148],"objectName":"up","endTime":28406},{"startTime":28487,"position":[382,179],"endTime":28643},{"startTime":28802,"position":[486,148],"endTime":28958},{"startTime":29118,"position":[315,241],"objectName":"right"},{"startTime":29276,"position":[421,274],"objectName":"up"},{"startTime":29434,"position":[315,241],"objectName":"right"},{"startTime":29592,"position":[258,176],"objectName":"up","endTime":29906},{"startTime":30066,"position":[391,184],"endTime":30222},{"startTime":30381,"position":[268,38],"objectName":"right"},{"startTime":30539,"position":[156,104]},{"startTime":30697,"position":[28,59],"objectName":"up"},{"startTime":30855,"position":[166,191],"objectName":"up","endTime":31011},{"startTime":31171,"position":[52,215],"objectName":"right"},{"startTime":31329,"position":[156,104],"endTime":31485},{"startTime":31644,"position":[79,138],"endTime":31800},{"startTime":31960,"position":[166,191],"objectName":"right","endTime":32116},{"startTime":32197,"position":[247,239],"objectName":"up"},{"startTime":32276,"position":[255,256]},{"startTime":32434,"position":[110,272],"objectName":"left"},{"startTime":32592,"position":[234,127]},{"startTime":32750,"position":[372,172],"objectName":"left"},{"startTime":32908,"position":[461,111],"objectName":"up","endTime":33064},{"startTime":33223,"position":[389,59],"objectName":"right"},{"startTime":33381,"position":[456,211],"objectName":"right"},{"startTime":33460,"position":[456,211]},{"startTime":33539,"position":[456,211],"objectName":"right"},{"startTime":33618,"position":[456,211],"objectName":"up"},{"startTime":33697,"position":[456,211]},{"startTime":33855,"position":[389,59],"endTime":34011},{"startTime":34171,"position":[194,44]},{"startTime":34329,"position":[56,123],"objectName":"up"},{"startTime":34487,"position":[159,176],"objectName":"right"},{"startTime":34644,"position":[21,255],"objectName":"up"},{"startTime":34802,"position":[199,248],"objectName":"up"},{"startTime":34960,"position":[133,95],"objectName":"right"},{"startTime":35118,"position":[34,224]},{"startTime":35276,"position":[199,162],"objectName":"up"},{"startTime":35434,"position":[316,115],"endTime":35590},{"startTime":35750,"position":[277,198],"objectName":"right","endTime":35985},{"startTime":36066,"position":[385,240],"endTime":36222},{"startTime":36381,"position":[464,218],"objectName":"right","endTime":36537},{"startTime":36697,"position":[449,300],"objectName":"left"},{"startTime":36855,"position":[384,156],"objectName":"left"},{"startTime":37013,"position":[287,284],"objectName":"up"},{"startTime":37171,"position":[379,353]},{"startTime":37250,"position":[379,353],"objectName":"right"},{"startTime":37329,"position":[379,353],"objectName":"left"},{"startTime":37487,"position":[306,197]},{"startTime":37644,"position":[206,249],"objectName":"right","endTime":37800},{"startTime":37960,"position":[0,345],"objectName":"up","endTime":38116},{"startTime":38276,"position":[176,160],"objectName":"up"},{"startTime":38434,"position":[93,136],"objectName":"up"},{"startTime":38513,"position":[93,136],"objectName":"up"},{"startTime":38592,"position":[93,136],"objectName":"up"},{"startTime":38671,"position":[93,136],"objectName":"left"},{"startTime":38750,"position":[93,136],"objectName":"right"},{"startTime":38908,"position":[188,273],"objectName":"right"},{"startTime":39066,"position":[259,118],"objectName":"left"},{"startTime":39223,"position":[14,64],"objectName":"up"},{"startTime":39855,"position":[15,69],"objectName":"left"},{"startTime":40487,"position":[152,273],"objectName":"up","endTime":40643},{"startTime":40802,"position":[201,205],"objectName":"left"},{"startTime":40960,"position":[273,364],"objectName":"left","endTime":41274},{"startTime":41434,"position":[118,193],"objectName":"right"},{"startTime":41592,"position":[267,143],"endTime":41748},{"startTime":41908,"position":[217,290],"objectName":"left","endTime":42064},{"startTime":42223,"position":[37,210],"objectName":"left","endTime":42379},{"startTime":42539,"position":[171,48],"endTime":42695},{"startTime":42855,"position":[349,190],"objectName":"up"},{"startTime":42934,"position":[349,190],"objectName":"left"},{"startTime":43013,"position":[349,190],"objectName":"right","endTime":43169},{"startTime":43329,"position":[311,112],"objectName":"left"},{"startTime":43487,"position":[496,133],"objectName":"right","endTime":43801},{"startTime":43960,"position":[466,55]},{"startTime":44118,"position":[445,217],"endTime":44274},{"startTime":44434,"position":[283,353],"endTime":44590},{"startTime":44750,"position":[249,210]},{"startTime":44829,"position":[249,210],"objectName":"up"},{"startTime":44908,"position":[249,210]},{"startTime":45066,"position":[380,305],"objectName":"right"},{"startTime":45223,"position":[396,147],"objectName":"right"},{"startTime":45381,"position":[283,126],"objectName":"up"},{"startTime":45460,"position":[283,126],"objectName":"right"},{"startTime":45539,"position":[283,126],"endTime":45695},{"startTime":45855,"position":[329,53],"objectName":"left"},{"startTime":46013,"position":[249,210],"objectName":"up","endTime":46327},{"startTime":46487,"position":[191,142]},{"startTime":46644,"position":[329,218],"objectName":"left","endTime":46800},{"startTime":46960,"position":[205,356],"objectName":"up","endTime":47116},{"startTime":47276,"position":[283,126],"objectName":"left","endTime":47432},{"startTime":47592,"position":[178,248],"endTime":47748},{"startTime":47908,"position":[24,140]},{"startTime":47987,"position":[24,140],"objectName":"right"},{"startTime":48066,"position":[24,140],"objectName":"right","endTime":48222},{"startTime":48381,"position":[181,29],"objectName":"left","endTime":48537},{"startTime":48697,"position":[203,214],"objectName":"up","endTime":48853},{"startTime":49013,"position":[57,225],"objectName":"left"},{"startTime":49171,"position":[258,152],"objectName":"left"},{"startTime":49329,"position":[227,293],"objectName":"left","endTime":49485},{"startTime":49644,"position":[456,305],"objectName":"left","endTime":49879},{"startTime":49960,"position":[342,275],"objectName":"right","endTime":50116},{"startTime":50276,"position":[425,63],"objectName":"up"},{"startTime":50434,"position":[474,203],"objectName":"left"},{"startTime":50592,"position":[321,159],"endTime":50906},{"startTime":51066,"position":[64,263],"objectName":"left","endTime":51380},{"startTime":51539,"position":[366,227],"objectName":"left","endTime":51695},{"startTime":51855,"position":[335,55]},{"startTime":52013,"position":[170,101],"objectName":"right"},{"startTime":52171,"position":[303,214],"objectName":"right"},{"startTime":52329,"position":[254,41],"objectName":"left"},{"startTime":52487,"position":[145,173],"objectName":"left"},{"startTime":52644,"position":[313,134],"objectName":"left"},{"startTime":52802,"position":[179,19],"objectName":"left"},{"startTime":52960,"position":[225,188],"objectName":"left"},{"startTime":53118,"position":[148,255],"objectName":"left","endTime":53432},{"startTime":53592,"position":[313,134],"objectName":"up","endTime":53906},{"startTime":54066,"position":[196,106],"endTime":54222},{"startTime":54381,"position":[225,188]},{"startTime":54539,"position":[52,108],"objectName":"left"},{"startTime":54697,"position":[213,22],"objectName":"up"},{"startTime":54855,"position":[292,94],"objectName":"up"},{"startTime":54934,"position":[292,94]},{"startTime":55013,"position":[292,94],"objectName":"right","endTime":55169},{"startTime":55329,"position":[481,74],"objectName":"left"},{"startTime":55408,"position":[481,74]},{"startTime":55487,"position":[481,74],"objectName":"right"},{"startTime":55566,"position":[481,74],"objectName":"left"},{"startTime":55644,"position":[481,74],"objectName":"left","endTime":55958},{"startTime":56118,"position":[454,348],"endTime":56432},{"startTime":56592,"position":[351,71],"objectName":"right","endTime":56748},{"startTime":56908,"position":[329,244],"objectName":"right"},{"startTime":57066,"position":[204,176],"objectName":"left"},{"startTime":57223,"position":[140,304]},{"startTime":57381,"position":[318,255],"objectName":"up"},{"startTime":57539,"position":[207,167],"objectName":"left"},{"startTime":57697,"position":[122,282],"objectName":"up"},{"startTime":57855,"position":[309,266],"objectName":"right"},{"startTime":58013,"position":[247,99],"objectName":"right"},{"startTime":58171,"position":[301,164],"objectName":"up","endTime":58485},{"startTime":58644,"position":[428,97],"objectName":"left","endTime":58800},{"startTime":58960,"position":[306,172],"objectName":"up"},{"startTime":59118,"position":[200,185],"objectName":"left","endTime":59274},{"startTime":59434,"position":[67,236],"objectName":"up","endTime":60380},{"startTime":60460,"position":[48,254],"objectName":"up"},{"startTime":60539,"position":[37,278]},{"startTime":60618,"position":[38,304]},{"startTime":60697,"position":[51,327]},{"startTime":61171,"position":[71,341],"objectName":"left"},{"startTime":61487,"position":[147,353],"objectName":"right"},{"startTime":61644,"position":[217,321],"objectName":"right","endTime":61802},{"startTime":61960,"position":[213,198],"objectName":"right"},{"startTime":62118,"position":[164,263],"objectName":"up","endTime":62434},{"startTime":62592,"position":[325,279],"objectName":"up","endTime":62750},{"startTime":62908,"position":[433,352],"objectName":"right","endTime":63066},{"startTime":63223,"position":[457,226],"endTime":63539},{"startTime":63697,"position":[393,179],"objectName":"right","endTime":64013},{"startTime":64171,"position":[105,219],"objectName":"left","endTime":64329},{"startTime":64487,"position":[266,152],"objectName":"right"},{"startTime":64644,"position":[184,132],"objectName":"left","endTime":64960},{"startTime":65118,"position":[319,214],"objectName":"left","endTime":65434},{"startTime":65592,"position":[453,154]},{"startTime":65750,"position":[510,206],"objectName":"up","endTime":66066},{"startTime":66223,"position":[378,300],"objectName":"up","endTime":66539},{"startTime":66697,"position":[295,371],"objectName":"up"},{"startTime":66855,"position":[197,254],"objectName":"up"},{"startTime":67013,"position":[185,331]},{"startTime":67171,"position":[123,282],"objectName":"right","endTime":67487},{"startTime":67644,"position":[251,182],"objectName":"left","endTime":67802},{"startTime":67960,"position":[425,109],"objectName":"left","endTime":68118},{"startTime":68276,"position":[308,37]},{"startTime":68434,"position":[251,90],"objectName":"left","endTime":68750},{"startTime":68908,"position":[63,128],"endTime":69224},{"startTime":69381,"position":[126,172],"objectName":"right"},{"startTime":69539,"position":[132,249],"objectName":"up","endTime":69697},{"startTime":70013,"position":[112,319],"objectName":"up"},{"startTime":70092,"position":[115,328]},{"startTime":70171,"position":[118,337],"objectName":"left"},{"startTime":70329,"position":[209,275],"objectName":"right","endTime":70645},{"startTime":70802,"position":[269,344],"objectName":"right","endTime":70960},{"startTime":71118,"position":[484,199],"objectName":"left","endTime":71276},{"startTime":71434,"position":[275,88],"objectName":"right","endTime":71592},{"startTime":71750,"position":[440,371],"objectName":"up","endTime":71908},{"startTime":72066,"position":[300,270],"objectName":"right"},{"startTime":72223,"position":[89,243],"objectName":"up"},{"startTime":72381,"position":[196,88]},{"startTime":72539,"position":[300,270],"objectName":"left"},{"startTime":72697,"position":[129,152]},{"startTime":72855,"position":[289,87]},{"startTime":73013,"position":[173,243]},{"startTime":73171,"position":[107,61],"objectName":"left"},{"startTime":73329,"position":[289,87],"objectName":"right","endTime":73487},{"startTime":73644,"position":[474,272],"objectName":"left","endTime":73802},{"startTime":73960,"position":[246,167],"objectName":"right","endTime":74118},{"startTime":74276,"position":[420,189],"endTime":74434},{"startTime":74592,"position":[240,262]},{"startTime":74750,"position":[367,352],"objectName":"right"},{"startTime":74908,"position":[213,336],"objectName":"left"},{"startTime":75066,"position":[307,215],"objectName":"left"},{"startTime":75223,"position":[149,273],"objectName":"right","endTime":75381},{"startTime":75539,"position":[192,35],"objectName":"right","endTime":75697},{"startTime":75855,"position":[376,132],"objectName":"up","endTime":76013},{"startTime":76171,"position":[222,207],"objectName":"right","endTime":76329},{"startTime":76487,"position":[376,254],"objectName":"up","endTime":76645},{"startTime":76802,"position":[284,138],"endTime":76960},{"startTime":77118,"position":[186,98],"objectName":"left"},{"startTime":77276,"position":[69,171],"objectName":"left"},{"startTime":77434,"position":[161,292],"objectName":"left"},{"startTime":77592,"position":[178,104],"objectName":"right"},{"startTime":77750,"position":[67,187],"objectName":"right"},{"startTime":77908,"position":[170,299]},{"startTime":78066,"position":[170,111]},{"startTime":78223,"position":[68,203],"objectName":"up"},{"startTime":78381,"position":[179,306],"objectName":"up","endTime":78539},{"startTime":78697,"position":[376,278],"endTime":78855},{"startTime":79013,"position":[286,213],"endTime":79171},{"startTime":79329,"position":[387,158],"objectName":"left","endTime":79487},{"startTime":79644,"position":[232,53],"objectName":"left"},{"startTime":80276,"position":[230,59]},{"startTime":80908,"position":[279,128]},{"startTime":81066,"position":[306,54],"objectName":"up","endTime":81382},{"startTime":81697,"position":[349,167],"objectName":"left"},{"startTime":81855,"position":[283,210],"objectName":"right"},{"startTime":82013,"position":[213,175]},{"startTime":82171,"position":[204,97],"objectName":"up","endTime":82329},{"startTime":82487,"position":[131,139],"endTime":82645},{"startTime":82802,"position":[52,119],"endTime":82960},{"startTime":83118,"position":[8,184],"endTime":83276},{"startTime":83434,"position":[138,321],"objectName":"up"},{"startTime":83592,"position":[204,362],"objectName":"up","endTime":83908},{"startTime":84223,"position":[331,347],"objectName":"right"},{"startTime":84381,"position":[380,286]},{"startTime":84539,"position":[399,210],"objectName":"right"},{"startTime":84618,"position":[400,187]},{"startTime":84697,"position":[397,164],"objectName":"up","endTime":84855},{"startTime":85013,"position":[312,144],"endTime":85171},{"startTime":85329,"position":[212,47],"objectName":"right"},{"startTime":85487,"position":[226,129],"objectName":"right","endTime":85803},{"startTime":85960,"position":[119,57],"objectName":"up"},{"startTime":86118,"position":[44,78],"objectName":"right","endTime":86434},{"startTime":86750,"position":[10,197],"objectName":"up","endTime":86908},{"startTime":87066,"position":[83,305],"objectName":"right"},{"startTime":87144,"position":[109,316],"objectName":"left"},{"startTime":87223,"position":[138,320],"objectName":"up","endTime":87381},{"startTime":87539,"position":[150,242]},{"startTime":87697,"position":[246,367],"objectName":"right","endTime":87855},{"startTime":88013,"position":[250,238],"objectName":"up"},{"startTime":88171,"position":[201,176],"objectName":"up","endTime":88329},{"startTime":88487,"position":[217,50],"objectName":"right","endTime":88803},{"startTime":88960,"position":[348,79],"objectName":"left","endTime":89118},{"startTime":89276,"position":[286,164],"objectName":"right","endTime":89434},{"startTime":89592,"position":[420,188]},{"startTime":89671,"position":[418,193],"objectName":"right"},{"startTime":89750,"position":[416,198]},{"startTime":89908,"position":[480,244],"objectName":"left"},{"startTime":90066,"position":[464,320]},{"startTime":90223,"position":[386,328]},{"startTime":90539,"position":[356,255],"objectName":"right","endTime":90697},{"startTime":90855,"position":[215,225],"objectName":"left"},{"startTime":91013,"position":[341,134],"objectName":"right","endTime":91171},{"startTime":91329,"position":[276,51],"objectName":"left"},{"startTime":91487,"position":[340,232],"objectName":"up"},{"startTime":91644,"position":[237,134],"objectName":"right","endTime":91802},{"startTime":91960,"position":[215,225],"objectName":"up"},{"startTime":92118,"position":[347,110],"objectName":"up"},{"startTime":92276,"position":[140,122],"objectName":"right","endTime":92434},{"startTime":92592,"position":[340,232],"endTime":92750},{"startTime":92908,"position":[91,230],"objectName":"right"},{"startTime":93066,"position":[205,363]},{"startTime":93223,"position":[170,194],"objectName":"left"},{"startTime":93381,"position":[107,360]},{"startTime":93539,"position":[5,194],"endTime":93697},{"startTime":93855,"position":[200,121],"endTime":94013},{"startTime":94171,"position":[167,281],"objectName":"up","endTime":94329},{"startTime":94487,"position":[123,83],"objectName":"right"},{"startTime":94644,"position":[257,258]},{"startTime":94723,"position":[263,286],"objectName":"left"},{"startTime":94802,"position":[258,314],"objectName":"right"},{"startTime":94960,"position":[170,194],"objectName":"right","endTime":95118},{"startTime":95276,"position":[360,73],"objectName":"right"},{"startTime":95434,"position":[487,182],"objectName":"left","endTime":95592},{"startTime":95750,"position":[291,130]},{"startTime":95908,"position":[387,303],"objectName":"up"},{"startTime":96066,"position":[317,214],"endTime":96224},{"startTime":96381,"position":[106,127],"objectName":"left","endTime":96539},{"startTime":96697,"position":[213,113],"objectName":"up"},{"startTime":96855,"position":[92,209]},{"startTime":97013,"position":[0,96],"objectName":"right"},{"startTime":97171,"position":[215,118]},{"startTime":97329,"position":[20,250],"objectName":"left","endTime":97487},{"startTime":97644,"position":[370,194],"objectName":"up","endTime":97802},{"startTime":97960,"position":[183,364],"objectName":"left","endTime":98118},{"startTime":98276,"position":[153,52],"objectName":"left","endTime":98434},{"startTime":98592,"position":[291,295],"objectName":"right"},{"startTime":98750,"position":[464,208],"objectName":"left"},{"startTime":98908,"position":[315,91],"objectName":"right"},{"startTime":99066,"position":[240,228],"objectName":"left"},{"startTime":99223,"position":[428,310]},{"startTime":99381,"position":[399,99]},{"startTime":99539,"position":[248,141],"objectName":"up"},{"startTime":99697,"position":[366,260],"objectName":"right"},{"startTime":99855,"position":[315,91],"objectName":"up","endTime":100013},{"startTime":100171,"position":[332,234],"objectName":"up"},{"startTime":100329,"position":[165,182],"objectName":"right","endTime":100487},{"startTime":100644,"position":[135,102],"objectName":"left"},{"startTime":100802,"position":[235,250],"objectName":"left"},{"startTime":100960,"position":[315,91],"objectName":"left"},{"startTime":101118,"position":[362,153],"objectName":"right","endTime":101276},{"startTime":101434,"position":[469,78],"objectName":"left","endTime":101750},{"startTime":101908,"position":[424,245],"objectName":"up","endTime":102224},{"startTime":102381,"position":[361,310],"objectName":"up","endTime":102537},{"startTime":102697,"position":[105,355]},{"startTime":102855,"position":[223,241],"objectName":"left"},{"startTime":103013,"position":[162,111],"objectName":"right"},{"startTime":103092,"position":[162,111],"objectName":"left"},{"startTime":103171,"position":[162,111],"objectName":"up"},{"startTime":103329,"position":[144,264],"endTime":103485},{"startTime":103644,"position":[258,78],"objectName":"right","endTime":103800},{"startTime":103960,"position":[93,172],"objectName":"left"},{"startTime":104118,"position":[223,241],"objectName":"right","endTime":104353},{"startTime":104434,"position":[332,247],"endTime":104590},{"startTime":104750,"position":[162,111],"objectName":"left"},{"startTime":104908,"position":[223,241],"endTime":105064},{"startTime":105223,"position":[93,172],"objectName":"right"},{"startTime":105381,"position":[247,102],"objectName":"up"},{"startTime":105539,"position":[381,174],"objectName":"left"},{"startTime":105618,"position":[381,174],"objectName":"left"},{"startTime":105697,"position":[381,174],"objectName":"right"},{"startTime":105855,"position":[162,111],"objectName":"up","endTime":106011},{"startTime":106171,"position":[340,99],"objectName":"left"},{"startTime":106329,"position":[196,188],"objectName":"left"},{"startTime":106487,"position":[381,174]},{"startTime":106644,"position":[158,259],"objectName":"left"},{"startTime":106802,"position":[302,170],"objectName":"left"},{"startTime":106960,"position":[117,184],"objectName":"right"},{"startTime":107118,"position":[221,340],"objectName":"right"},{"startTime":107197,"position":[224,333],"objectName":"left"},{"startTime":107276,"position":[227,326],"objectName":"right"},{"startTime":107355,"position":[230,319],"objectName":"up"},{"startTime":107434,"position":[233,312],"objectName":"right","endTime":107590},{"startTime":107750,"position":[445,359]},{"startTime":107908,"position":[376,234],"objectName":"right","endTime":108064},{"startTime":108223,"position":[496,62],"objectName":"up","endTime":108379},{"startTime":108539,"position":[276,184],"objectName":"left"},{"startTime":108697,"position":[376,234],"endTime":108853},{"startTime":109013,"position":[257,109],"objectName":"up","endTime":109169},{"startTime":109329,"position":[276,184],"objectName":"right"},{"startTime":109487,"position":[185,73]},{"startTime":109644,"position":[357,154],"objectName":"up"},{"startTime":109802,"position":[214,255],"objectName":"left"},{"startTime":109960,"position":[76,145],"objectName":"left","endTime":110116},{"startTime":110276,"position":[130,216],"endTime":110511},{"startTime":110592,"position":[150,322],"objectName":"up","endTime":110748},{"startTime":110908,"position":[372,364],"objectName":"up","endTime":111064},{"startTime":111223,"position":[332,201]},{"startTime":111381,"position":[488,111],"objectName":"left"},{"startTime":111539,"position":[457,236]},{"startTime":111697,"position":[367,80],"objectName":"left"},{"startTime":111855,"position":[212,149],"objectName":"right"},{"startTime":112013,"position":[302,305],"objectName":"right"},{"startTime":112171,"position":[411,155],"objectName":"left"},{"startTime":112250,"position":[409,162]},{"startTime":112329,"position":[408,169]},{"startTime":112408,"position":[407,176]},{"startTime":112487,"position":[405,183],"objectName":"up","endTime":112643},{"startTime":112802,"position":[215,239],"objectName":"left","endTime":112958},{"startTime":113118,"position":[289,114],"objectName":"right"},{"startTime":113197,"position":[289,114],"objectName":"up"},{"startTime":113276,"position":[289,114],"objectName":"right"},{"startTime":113434,"position":[294,236],"objectName":"right","endTime":113590},{"startTime":113750,"position":[205,130],"objectName":"up"},{"startTime":113908,"position":[373,104],"objectName":"left"},{"startTime":114066,"position":[207,211],"objectName":"left","endTime":114301},{"startTime":114381,"position":[123,144],"objectName":"right","endTime":114537},{"startTime":114697,"position":[207,211],"endTime":114853},{"startTime":115013,"position":[67,209],"objectName":"up"},{"startTime":115171,"position":[205,130],"objectName":"right"},{"startTime":115329,"position":[279,253],"objectName":"up","endTime":115485},{"startTime":115644,"position":[335,176],"objectName":"left"},{"startTime":115723,"position":[335,176]},{"startTime":115802,"position":[335,176]},{"startTime":115960,"position":[428,134],"endTime":116116},{"startTime":116276,"position":[359,58],"objectName":"right"},{"startTime":116434,"position":[416,219],"objectName":"left"},{"startTime":116592,"position":[238,168],"objectName":"right"},{"startTime":116750,"position":[359,58],"objectName":"left"},{"startTime":116908,"position":[294,254],"objectName":"right"},{"startTime":117066,"position":[144,93],"objectName":"left"},{"startTime":117223,"position":[238,168]},{"startTime":117302,"position":[235,175]},{"startTime":117381,"position":[232,182]},{"startTime":117460,"position":[229,189]},{"startTime":117539,"position":[226,196],"objectName":"left","endTime":117695},{"startTime":117855,"position":[0,180],"objectName":"up"},{"startTime":118013,"position":[120,308]},{"startTime":118092,"position":[120,308],"objectName":"left"},{"startTime":118171,"position":[120,308]},{"startTime":118329,"position":[95,190],"endTime":118485},{"startTime":118644,"position":[71,37],"objectName":"left"},{"startTime":118802,"position":[228,84],"endTime":118958},{"startTime":119118,"position":[456,141],"objectName":"up","endTime":119274},{"startTime":119434,"position":[220,208],"objectName":"right","endTime":119590},{"startTime":119750,"position":[466,292],"objectName":"right","endTime":119906},{"startTime":120066,"position":[276,308],"objectName":"left","endTime":120222},{"startTime":120381,"position":[141,199],"objectName":"right"},{"startTime":120539,"position":[279,131],"objectName":"up","endTime":120774},{"startTime":120855,"position":[391,161],"endTime":121011},{"startTime":121171,"position":[329,48],"objectName":"left"},{"startTime":121329,"position":[236,60],"endTime":121645},{"startTime":121802,"position":[281,212],"objectName":"right","endTime":122118},{"startTime":122276,"position":[339,344]},{"startTime":122355,"position":[340,350]},{"startTime":122434,"position":[342,356],"objectName":"up"},{"startTime":122592,"position":[196,231],"objectName":"right"},{"startTime":123066,"position":[363,169],"objectName":"right"},{"startTime":123539,"position":[138,168],"objectName":"left"},{"startTime":124013,"position":[421,238],"objectName":"left"},{"startTime":124487,"position":[206,127],"objectName":"left"},{"startTime":124960,"position":[499,175],"objectName":"right"},{"startTime":125434,"position":[134,256],"objectName":"right"},{"startTime":125908,"position":[416,156],"objectName":"up"},{"startTime":126381,"position":[77,105]},{"startTime":126855,"position":[429,249],"objectName":"right"},{"startTime":127171,"position":[154,184],"objectName":"up"},{"startTime":127487,"position":[416,156],"objectName":"right"},{"startTime":127644,"position":[350,259],"objectName":"right","endTime":127802},{"startTime":127960,"position":[338,110],"objectName":"right"},{"startTime":128039,"position":[338,110],"objectName":"right"},{"startTime":128118,"position":[338,110],"objectName":"up"},{"startTime":128276,"position":[227,222],"objectName":"right","endTime":128513},{"startTime":128592,"position":[81,206],"objectName":"left","endTime":128750},{"startTime":128908,"position":[34,108],"objectName":"left"},{"startTime":128987,"position":[34,108],"objectName":"right"},{"startTime":129066,"position":[34,108],"objectName":"up"},{"startTime":129223,"position":[169,235],"objectName":"up","endTime":129381},{"startTime":129539,"position":[52,236],"objectName":"right"},{"startTime":129697,"position":[213,131]},{"startTime":129855,"position":[239,316]},{"startTime":130013,"position":[52,236]},{"startTime":130171,"position":[272,209],"objectName":"left"},{"startTime":130250,"position":[270,204]},{"startTime":130329,"position":[268,199],"objectName":"up"},{"startTime":130487,"position":[147,70],"objectName":"up"},{"startTime":130566,"position":[145,75],"objectName":"up"},{"startTime":130644,"position":[143,80],"objectName":"up"},{"startTime":130802,"position":[327,45],"objectName":"up","endTime":131039},{"startTime":131118,"position":[455,95],"objectName":"right","endTime":131276},{"startTime":131434,"position":[256,113],"objectName":"left","endTime":131668},{"startTime":131750,"position":[108,162],"endTime":131984},{"startTime":132066,"position":[167,184],"objectName":"up"},{"startTime":132144,"position":[177,193],"objectName":"up"},{"startTime":132223,"position":[184,205],"objectName":"right"},{"startTime":132302,"position":[187,219],"objectName":"left"},{"startTime":132381,"position":[186,233],"objectName":"up"},{"startTime":132460,"position":[181,246],"objectName":"up"},{"startTime":132539,"position":[172,257]},{"startTime":132618,"position":[160,265]},{"startTime":132697,"position":[146,270],"objectName":"up"}],"AudioFilename":"song.mp3","TitleUnicode":"アートコア神社"}